clientcentral/Exceptions.py
clientcentral/__init__.py
clientcentral/clientcentral.py
clientcentral/query.py
clientcentral/roles.py
clientcentral/ticket.py
clientcentral/ticketformatting.py
clientcentral/users_client.py
clientcentral/model/Attachment.py
clientcentral/model/Button.py
clientcentral/model/Change.py
clientcentral/model/ChangeEvent.py
clientcentral/model/Comment.py
clientcentral/model/Role.py
clientcentral/model/Status.py
clientcentral/model/TicketEvent.py
clientcentral/model/TicketType.py
clientcentral/model/User.py
clientcentral/model/__init__.py
clientcentral-12.5.10.dist-info/licenses/AUTHORS.rst
clientcentral-12.5.10.dist-info/licenses/LICENSE
clientcentral-12.5.10.dist-info/METADATA
clientcentral-12.5.10.dist-info/WHEEL
clientcentral-12.5.10.dist-info/top_level.txt
clientcentral-12.5.10.dist-info/RECORD
