Metadata-Version: 2.4
Name: clientcentral
Version: 12.5.10
Summary: Client Central Python API.
Author-email: Thomas Scholtz <thomas@labs.epiuse.com>
License: GNU GENERAL PUBLIC LICENSE
Project-URL: Homepage, https://github.com/EPI-USE-Labs/client-central-python-api
Keywords: ClientCentral,Client,EPI-USE Labs,EPI-USE,Client-Central
Classifier: Development Status :: 5 - Production/Stable
Classifier: Intended Audience :: Developers
Classifier: Natural Language :: English
Classifier: Programming Language :: Python :: 3.13
Requires-Python: >=3.13
License-File: LICENSE
License-File: AUTHORS.rst
Requires-Dist: beautifulsoup4>=4.12.3
Requires-Dist: aiohttp>=3.11.4
Requires-Dist: ujson>=5.10.0
Dynamic: license-file
